qpalm-1.2.6.dist-info/RECORD
qpalm-1.2.6.dist-info/WHEEL
qpalm-1.2.6.dist-info/entry_points.txt
qpalm-1.2.6.dist-info/METADATA
qpalm-1.2.6.dist-info/licenses/LICENSE
qpalm/_qpalm.pyi
qpalm/__init__.pyi
qpalm/__init__.py
qpalm/py.typed
qpalm/_qpalm.cpython-314-darwin.so
qpalm/_qpalm_d.cpython-314-darwin.so
