Metadata-Version: 2.4
Name: qpalm
Version: 1.2.6
Summary: Proximal Augmented Lagrangian method for Quadratic Programs
Keywords: optimization,augmented-lagrangian,proximal,qp,quadratic-programming,nonconvex,ladel
Author: Ben Hermans
Maintainer-Email: Pieter Pas <pieter.p.dev@outlook.com>
License-Expression: LGPL-3.0-or-later
License-File: LICENSE
Classifier: Development Status :: 5 - Production/Stable
Classifier: Topic :: Scientific/Engineering
Classifier: Topic :: Scientific/Engineering :: Mathematics
Classifier: Programming Language :: Python :: 3
Classifier: Programming Language :: Python :: 3.9
Classifier: Programming Language :: Python :: 3.10
Classifier: Programming Language :: Python :: 3.11
Classifier: Programming Language :: Python :: 3.12
Classifier: Programming Language :: Python :: 3.13
Classifier: Programming Language :: Python :: 3.14
Classifier: Programming Language :: C
Classifier: Programming Language :: C++
Classifier: Operating System :: POSIX :: Linux
Classifier: Operating System :: Microsoft :: Windows
Classifier: Operating System :: MacOS
Classifier: Typing :: Typed
Project-URL: Source, https://github.com/kul-optec/QPALM
Project-URL: Documentation, https://kul-optec.github.io/QPALM
Project-URL: Tracker, https://github.com/kul-optec/QPALM/issues
Requires-Python: >=3.9
Requires-Dist: numpy<3,>=1.19
Requires-Dist: scipy<2,>=1.6
Provides-Extra: debug
Requires-Dist: qpalm-debug==1.2.6; extra == "debug"
Provides-Extra: test
Requires-Dist: pytest<9,>=7.2.0; extra == "test"
